tap_fulfil
