Metadata-Version: 1.1
Name: tap-fulfil
Version: 0.1.7
Summary: Singer.io tap for extracting data
Home-page: https://www.fulfil.io
Author: Fulfil.IO Inc.
Author-email: UNKNOWN
License: UNKNOWN
Platform: UNKNOWN
Classifier: Programming Language :: Python :: 3 :: Only
